{"is_source_file": false, "format": "CSS", "description": "CSS stylesheet defining styles for body and code elements in a web project.", "external_files": [], "external_methods": [], "published": [], "classes": [], "methods": [], "calls": [], "search-terms": ["body styles", "font-family", "CSS stylesheet", "frontend styles"], "state": 2, "file_id": 7, "knowledge_revision": 20, "git_revision": "be075746e4216fbda5dede47daae99e8e37b6491", "hash": "6c2104b8d219ed99234ae2d6329f4357", "format-version": 4, "code-base-name": "tic_tac_toe_frontend", "filename": "tic_tac_toe_frontend/src/index.css", "revision_history": [{"20": "be075746e4216fbda5dede47daae99e8e37b6491"}]}